mssdk/__init__.py
mssdk/air/__init__.py
mssdk/air/air_hebei.py
mssdk/air/air_zhenqi.py
mssdk/air/cons.py
mssdk/air/crypto.js
mssdk/air/outcrypto.js
mssdk/air/time_and_date.py
mssdk/article/__init__.py
mssdk/article/agoyal.py
mssdk/article/cons.py
mssdk/article/epu_index.py
mssdk/article/ff_factor.py
mssdk/article/fred_md.py
mssdk/article/risk_rv.py
mssdk/bank/__init__.py
mssdk/bank/bank_banker.py
mssdk/bank/bank_cbirc_2020.py
mssdk/bank/cons.py
mssdk/bond/__init__.py
mssdk/bond/bond_bank.py
mssdk/bond/bond_china_money.py
mssdk/bond/bond_convert.py
mssdk/bond/bond_em.py
mssdk/bond/bond_futures.py
mssdk/bond/bond_investing.py
mssdk/bond/bond_issue_cninfo.py
mssdk/bond/bond_summary.py
mssdk/bond/bond_zh_cov_sina.py
mssdk/bond/bond_zh_sina.py
mssdk/bond/china_bond.py
mssdk/bond/china_repo.py
mssdk/bond/cons.py
mssdk/bond/zh_bond_cov_sina.py
mssdk/bond/zh_bond_sina.py
mssdk/charity/__init__.py
mssdk/charity/charity_china.py
mssdk/cost/__init__.py
mssdk/cost/cons.py
mssdk/cost/cost_living.py
mssdk/crypto/__init__.py
mssdk/crypto/crypto_bitcoin_cme.py
mssdk/crypto/crypto_crix.py
mssdk/crypto/crypto_hist_investing.py
mssdk/crypto/crypto_hold.py
mssdk/currency/__init__.py
mssdk/currency/currency.py
mssdk/currency/currency_sina_china_bank.py
mssdk/economic/__init__.py
mssdk/economic/cons.py
mssdk/economic/macro_australia.py
mssdk/economic/macro_bank.py
mssdk/economic/macro_canada.py
mssdk/economic/macro_china.py
mssdk/economic/macro_china_hk.py
mssdk/economic/macro_constitute.py
mssdk/economic/macro_euro.py
mssdk/economic/macro_germany.py
mssdk/economic/macro_japan.py
mssdk/economic/macro_other.py
mssdk/economic/macro_swiss.py
mssdk/economic/macro_uk.py
mssdk/economic/macro_usa.py
mssdk/economic/marco_cnbs.py
mssdk/energy/__init__.py
mssdk/energy/energy_carbon.py
mssdk/energy/energy_oil.py
mssdk/event/__init__.py
mssdk/event/cons.py
mssdk/event/covid.py
mssdk/event/franchise.py
mssdk/file_fold/__init__.py
mssdk/file_fold/calendar.json
mssdk/fortune/__init__.py
mssdk-0.0.38.dist-info/LICENSE
mssdk-0.0.38.dist-info/METADATA
mssdk-0.0.38.dist-info/WHEEL
mssdk-0.0.38.dist-info/top_level.txt
mssdk-0.0.38.dist-info/RECORD
