Metadata-Version: 2.1
Name: mssdk
Version: 0.0.38
Summary: mssdk is an elegant and simple financial data interface library for Python, built for human beings!
Home-page: https://github.com/cdmaxsmart/mssdk
Author: MaxsWell
Author-email: mssdk@mssdk.email.cn
License: MIT
Keywords: stock,option,futures,fund,bond,index,air,finance,spider,quant,quantitative,investment,trading,algotrading,data
Classifier: Programming Language :: Python :: 3.7
Classifier: Programming Language :: Python :: 3.8
Classifier: Programming Language :: Python :: 3.9
Classifier: Programming Language :: Python :: 3.10
Classifier: License :: OSI Approved :: MIT License
Classifier: Operating System :: OS Independent
Requires-Python: >=3.7
License-File: LICENSE
Requires-Dist: beautifulsoup4 (>=4.9.1)
Requires-Dist: lxml (>=4.2.1)
Requires-Dist: matplotlib (>=3.1.1)
Requires-Dist: numpy (>=1.15.4)
Requires-Dist: pandas (>=0.25)
Requires-Dist: requests (>=2.22.0)
Requires-Dist: pillow (>=6.2.0)
Requires-Dist: pypinyin (>=0.35.0)
Requires-Dist: websocket-client (>=0.56.0)
Requires-Dist: html5lib (>=1.0.1)
Requires-Dist: xlrd (>=1.2.0)
Requires-Dist: urllib3 (>=1.25.8)
Requires-Dist: tqdm (>=4.43.0)
Requires-Dist: openpyxl (>=3.0.3)
Requires-Dist: jsonpath (>=0.82)
Requires-Dist: tabulate (>=0.8.6)
Requires-Dist: decorator (>=4.4.2)
Requires-Dist: py-mini-racer (>=0.6.0)
Requires-Dist: pyyaml
